tccl/__init__.py
tccl-0.0.1.dist-info/METADATA
tccl-0.0.1.dist-info/WHEEL
tccl-0.0.1.dist-info/top_level.txt
tccl-0.0.1.dist-info/RECORD
