Metadata-Version: 2.1
Name: tccl
Version: 0.0.1
Summary: TensorPipe Collective Communication Library
Author-email: Luca Wehrstedt <luca.wehrstedt@gmail.com>
Project-URL: Homepage, https://github.com/fairinternal/tccl
Classifier: Programming Language :: Python :: 3
Classifier: License :: OSI Approved :: MIT License
Classifier: Operating System :: OS Independent
Requires-Python: >=3.7
